auto_mouse_clicker_KingDavidJnr/__init__.py
auto_mouse_clicker_KingDavidJnr/auto_clicker.py
auto_mouse_clicker_KingDavidJnr-0.0.1.dist-info/LICENSE
auto_mouse_clicker_KingDavidJnr-0.0.1.dist-info/METADATA
auto_mouse_clicker_KingDavidJnr-0.0.1.dist-info/WHEEL
auto_mouse_clicker_KingDavidJnr-0.0.1.dist-info/top_level.txt
auto_mouse_clicker_KingDavidJnr-0.0.1.dist-info/RECORD
