Metadata-Version: 2.1
Name: auto_mouse_clicker_KingDavidJnr
Version: 0.0.1
Summary: Python auto-clicker script that automates mouse clicks at defined intervals and visually indicates each click with a bubble overlay.
Author-email: David Oduse <odusedavid@gmail.com>
Project-URL: Homepage, https://github.com/KingDavidJnr/auto-mouse-clicker
Project-URL: Issues, https://github.com/KingDavidJnr/auto-mouse-clicker/issues
Classifier: Programming Language :: Python :: 3
Classifier: License :: OSI Approved :: MIT License
Classifier: Operating System :: OS Independent
Requires-Python: >=3.8
License-File: LICENSE
